README.rst
setup.py
examples/__init__.py
examples/ec2/__init__.py
examples/ec2/ec2_static_ip.py
tropostack/__init__.py
tropostack/base.py
tropostack/cli.py
tropostack/conf_loaders.py
tropostack/exceptions.py
tropostack.egg-info/PKG-INFO
tropostack.egg-info/SOURCES.txt
tropostack.egg-info/dependency_links.txt
tropostack.egg-info/requires.txt
tropostack.egg-info/top_level.txt