Metadata-Version: 2.1
Name: tropostack
Version: 0.4.2
Summary: CLI/workflow lib around for management of CloudFormation stacks
Home-page: https://github.com/topostack/tropostack
Author: tie
Author-email: tropostack@morp.org
License: MIT
Platform: UNKNOWN
Classifier: Development Status :: 2 - Pre-Alpha
Classifier: License :: OSI Approved :: MIT License
Classifier: Programming Language :: Python
Classifier: Programming Language :: Python :: 3
Classifier: Programming Language :: Python :: 3.4
Classifier: Programming Language :: Python :: 3.5
Classifier: Programming Language :: Python :: 3.6
Classifier: Programming Language :: Python :: 3.7
